[
  {
    "season": "2026",
    "team": "KC",
    "gp": "84",
    "min": "328",
    "pts": ".290",
    "reb": "12",
    "ast": "36",
    "stl": "30",
    "blk": "62",
    "fgPct": "-",
    "fg3Pct": "-",
    "ftPct": "-",
    "to": "-"
  },
  {
    "season": "2025",
    "team": "KC",
    "gp": "157",
    "min": "623",
    "pts": ".295",
    "reb": "23",
    "ast": "88",
    "stl": "38",
    "blk": "125",
    "fgPct": "-",
    "fg3Pct": "-",
    "ftPct": "-",
    "to": "-"
  },
  {
    "season": "2024",
    "team": "KC",
    "gp": "161",
    "min": "636",
    "pts": ".332",
    "reb": "32",
    "ast": "109",
    "stl": "31",
    "blk": "106",
    "fgPct": "-",
    "fg3Pct": "-",
    "ftPct": "-",
    "to": "-"
  },
  {
    "season": "2023",
    "team": "KC",
    "gp": "158",
    "min": "641",
    "pts": ".276",
    "reb": "30",
    "ast": "96",
    "stl": "49",
    "blk": "121",
    "fgPct": "-",
    "fg3Pct": "-",
    "ftPct": "-",
    "to": "-"
  },
  {
    "season": "2022",
    "team": "KC",
    "gp": "150",
    "min": "591",
    "pts": ".254",
    "reb": "20",
    "ast": "80",
    "stl": "30",
    "blk": "135",
    "fgPct": "-",
    "fg3Pct": "-",
    "ftPct": "-",
    "to": "-"
  }
]
