[
  {
    "season": "2026",
    "team": "LAD",
    "gp": "77",
    "min": "293",
    "pts": ".297",
    "reb": "18",
    "ast": "50",
    "stl": "6",
    "blk": "83",
    "fgPct": "-",
    "fg3Pct": "-",
    "ftPct": "-",
    "to": "-"
  },
  {
    "season": "2025",
    "team": "LAD",
    "gp": "158",
    "min": "611",
    "pts": ".282",
    "reb": "55",
    "ast": "102",
    "stl": "20",
    "blk": "187",
    "fgPct": "-",
    "fg3Pct": "-",
    "ftPct": "-",
    "to": "-"
  },
  {
    "season": "2024",
    "team": "LAD",
    "gp": "159",
    "min": "636",
    "pts": ".310",
    "reb": "54",
    "ast": "130",
    "stl": "59",
    "blk": "162",
    "fgPct": "-",
    "fg3Pct": "-",
    "ftPct": "-",
    "to": "-"
  },
  {
    "season": "2023",
    "team": "LAA",
    "gp": "135",
    "min": "497",
    "pts": ".304",
    "reb": "44",
    "ast": "95",
    "stl": "20",
    "blk": "143",
    "fgPct": "-",
    "fg3Pct": "-",
    "ftPct": "-",
    "to": "-"
  },
  {
    "season": "2022",
    "team": "LAA",
    "gp": "157",
    "min": "586",
    "pts": ".273",
    "reb": "34",
    "ast": "95",
    "stl": "11",
    "blk": "161",
    "fgPct": "-",
    "fg3Pct": "-",
    "ftPct": "-",
    "to": "-"
  },
  {
    "season": "2021",
    "team": "LAA",
    "gp": "155",
    "min": "537",
    "pts": ".257",
    "reb": "46",
    "ast": "100",
    "stl": "26",
    "blk": "189",
    "fgPct": "-",
    "fg3Pct": "-",
    "ftPct": "-",
    "to": "-"
  },
  {
    "season": "2020",
    "team": "LAA",
    "gp": "44",
    "min": "153",
    "pts": ".190",
    "reb": "7",
    "ast": "24",
    "stl": "7",
    "blk": "50",
    "fgPct": "-",
    "fg3Pct": "-",
    "ftPct": "-",
    "to": "-"
  },
  {
    "season": "2019",
    "team": "LAA",
    "gp": "106",
    "min": "384",
    "pts": ".286",
    "reb": "18",
    "ast": "62",
    "stl": "12",
    "blk": "110",
    "fgPct": "-",
    "fg3Pct": "-",
    "ftPct": "-",
    "to": "-"
  },
  {
    "season": "2018",
    "team": "LAA",
    "gp": "104",
    "min": "326",
    "pts": ".285",
    "reb": "22",
    "ast": "61",
    "stl": "10",
    "blk": "102",
    "fgPct": "-",
    "fg3Pct": "-",
    "ftPct": "-",
    "to": "-"
  }
]
