{
  "id": "raleica01",
  "espnId": "41292",
  "slug": "raleica01",
  "name": "Cal Raleigh",
  "sport": "mlb",
  "position": "C",
  "team": "SEA",
  "headshot": "media/headshots/mlb/raleica01.png",
  "headshotSource": "https://a.espncdn.com/i/headshots/mlb/players/full/41292.png",
  "legend": false,
  "seasonHistory": [
    {
      "season": "2026",
      "team": "SEA",
      "gp": "61",
      "min": "229",
      "pts": ".170",
      "reb": "9",
      "ast": "29",
      "stl": "2",
      "blk": "84",
      "fgPct": "-",
      "fg3Pct": "-",
      "ftPct": "-",
      "to": "-"
    },
    {
      "season": "2025",
      "team": "SEA",
      "gp": "159",
      "min": "596",
      "pts": ".247",
      "reb": "60",
      "ast": "125",
      "stl": "14",
      "blk": "188",
      "fgPct": "-",
      "fg3Pct": "-",
      "ftPct": "-",
      "to": "-"
    },
    {
      "season": "2024",
      "team": "SEA",
      "gp": "153",
      "min": "546",
      "pts": ".220",
      "reb": "34",
      "ast": "100",
      "stl": "6",
      "blk": "176",
      "fgPct": "-",
      "fg3Pct": "-",
      "ftPct": "-",
      "to": "-"
    },
    {
      "season": "2023",
      "team": "SEA",
      "gp": "145",
      "min": "513",
      "pts": ".232",
      "reb": "30",
      "ast": "75",
      "stl": "0",
      "blk": "158",
      "fgPct": "-",
      "fg3Pct": "-",
      "ftPct": "-",
      "to": "-"
    },
    {
      "season": "2022",
      "team": "SEA",
      "gp": "119",
      "min": "370",
      "pts": ".211",
      "reb": "27",
      "ast": "63",
      "stl": "1",
      "blk": "122",
      "fgPct": "-",
      "fg3Pct": "-",
      "ftPct": "-",
      "to": "-"
    },
    {
      "season": "2021",
      "team": "SEA",
      "gp": "47",
      "min": "139",
      "pts": ".180",
      "reb": "2",
      "ast": "13",
      "stl": "0",
      "blk": "52",
      "fgPct": "-",
      "fg3Pct": "-",
      "ftPct": "-",
      "to": "-"
    }
  ],
  "recentGames": [
    {
      "date": "Jul 8",
      "matchup": "@ MIA",
      "result": "L 2-0",
      "min": "4",
      "pts": "—",
      "reb": "0",
      "ast": "0",
      "stl": "—",
      "blk": "1"
    },
    {
      "date": "Jul 7",
      "matchup": "@ MIA",
      "result": "L 6-5 F/10",
      "min": "5",
      "pts": "—",
      "reb": "0",
      "ast": "1",
      "stl": "—",
      "blk": "2"
    },
    {
      "date": "Jul 5",
      "matchup": "vs TOR",
      "result": "W 4-0",
      "min": "3",
      "pts": "—",
      "reb": "0",
      "ast": "1",
      "stl": "—",
      "blk": "2"
    },
    {
      "date": "Jul 4",
      "matchup": "vs TOR",
      "result": "W 11-0",
      "min": "4",
      "pts": "—",
      "reb": "1",
      "ast": "3",
      "stl": "—",
      "blk": "0"
    },
    {
      "date": "Jul 4",
      "matchup": "vs TOR",
      "result": "L 2-0",
      "min": "4",
      "pts": "—",
      "reb": "0",
      "ast": "0",
      "stl": "—",
      "blk": "2"
    }
  ],
  "sources": [
    "espn"
  ],
  "ingestedAt": "2026-07-09T10:49:19.357Z",
  "statsSyncedAt": "2026-07-09T10:49:19.357Z",
  "active": true,
  "profileSyncedAt": "2026-06-25T15:42:29.870Z",
  "details": {
    "jersey": "29",
    "height": "6' 2\"",
    "weight": "235 lbs",
    "debutYear": 2021,
    "college": "Florida State",
    "awards": [],
    "headshotSource": "https://a.espncdn.com/i/headshots/mlb/players/full/41292.png"
  },
  "detailSyncedAt": "2026-07-01T13:38:38.748Z"
}
