{
  "id": "kittlge00",
  "espnId": "3040151",
  "slug": "kittlge00",
  "name": "George Kittle",
  "sport": "nfl",
  "position": "TE",
  "team": "SF",
  "headshot": "media/headshots/nfl/kittlge00.png",
  "headshotSource": "https://a.espncdn.com/i/headshots/nfl/players/full/3040151.png",
  "legend": false,
  "seasonHistory": [
    {
      "season": "2025",
      "team": "SF",
      "gp": "11",
      "min": "-",
      "pts": "628",
      "reb": "7",
      "ast": "-",
      "stl": "-",
      "blk": "-",
      "fgPct": "-",
      "fg3Pct": "-",
      "ftPct": "-",
      "to": "0"
    },
    {
      "season": "2024",
      "team": "SF",
      "gp": "15",
      "min": "-",
      "pts": "1,106",
      "reb": "8",
      "ast": "-",
      "stl": "-",
      "blk": "-",
      "fgPct": "-",
      "fg3Pct": "-",
      "ftPct": "-",
      "to": "0"
    },
    {
      "season": "2023",
      "team": "SF",
      "gp": "16",
      "min": "-",
      "pts": "1,020",
      "reb": "6",
      "ast": "-",
      "stl": "-",
      "blk": "-",
      "fgPct": "-",
      "fg3Pct": "-",
      "ftPct": "-",
      "to": "0"
    },
    {
      "season": "2022",
      "team": "SF",
      "gp": "15",
      "min": "-",
      "pts": "765",
      "reb": "11",
      "ast": "-",
      "stl": "-",
      "blk": "-",
      "fgPct": "-",
      "fg3Pct": "-",
      "ftPct": "-",
      "to": "1"
    },
    {
      "season": "2021",
      "team": "SF",
      "gp": "14",
      "min": "-",
      "pts": "910",
      "reb": "6",
      "ast": "-",
      "stl": "-",
      "blk": "-",
      "fgPct": "-",
      "fg3Pct": "-",
      "ftPct": "-",
      "to": "2"
    },
    {
      "season": "2020",
      "team": "SF",
      "gp": "8",
      "min": "-",
      "pts": "634",
      "reb": "2",
      "ast": "-",
      "stl": "-",
      "blk": "-",
      "fgPct": "-",
      "fg3Pct": "-",
      "ftPct": "-",
      "to": "0"
    },
    {
      "season": "2019",
      "team": "SF",
      "gp": "14",
      "min": "-",
      "pts": "1,053",
      "reb": "5",
      "ast": "-",
      "stl": "-",
      "blk": "-",
      "fgPct": "-",
      "fg3Pct": "-",
      "ftPct": "-",
      "to": "1"
    },
    {
      "season": "2018",
      "team": "SF",
      "gp": "16",
      "min": "-",
      "pts": "1,377",
      "reb": "5",
      "ast": "-",
      "stl": "-",
      "blk": "-",
      "fgPct": "-",
      "fg3Pct": "-",
      "ftPct": "-",
      "to": "0"
    },
    {
      "season": "2017",
      "team": "SF",
      "gp": "15",
      "min": "-",
      "pts": "515",
      "reb": "2",
      "ast": "-",
      "stl": "-",
      "blk": "-",
      "fgPct": "-",
      "fg3Pct": "-",
      "ftPct": "-",
      "to": "0"
    }
  ],
  "recentGames": [
    {
      "date": "Jan 11",
      "matchup": "@ PHI",
      "result": "W 23-19",
      "min": "—",
      "pts": "6",
      "reb": "0",
      "ast": "—",
      "stl": "—",
      "blk": "—"
    },
    {
      "date": "Jan 3",
      "matchup": "vs SEA",
      "result": "L 13-3",
      "min": "—",
      "pts": "29",
      "reb": "0",
      "ast": "—",
      "stl": "—",
      "blk": "—"
    },
    {
      "date": "Dec 22",
      "matchup": "@ IND",
      "result": "W 48-27",
      "min": "—",
      "pts": "115",
      "reb": "1",
      "ast": "—",
      "stl": "—",
      "blk": "—"
    },
    {
      "date": "Dec 14",
      "matchup": "vs TEN",
      "result": "W 37-24",
      "min": "—",
      "pts": "88",
      "reb": "1",
      "ast": "—",
      "stl": "—",
      "blk": "—"
    },
    {
      "date": "Nov 30",
      "matchup": "@ CLE",
      "result": "W 26-8",
      "min": "—",
      "pts": "67",
      "reb": "0",
      "ast": "—",
      "stl": "—",
      "blk": "—"
    }
  ],
  "sources": [
    "espn"
  ],
  "ingestedAt": "2026-06-15T15:26:14.551Z"
}
