[
  {
    "season": "",
    "gp": "-",
    "min": "-",
    "pts": "-",
    "reb": "0/0",
    "ast": "0/0",
    "stl": "-",
    "blk": "-",
    "fgPct": "-",
    "fg3Pct": "-",
    "ftPct": "-",
    "to": "-"
  },
  {
    "season": "",
    "gp": "-",
    "min": "-",
    "pts": "-",
    "reb": "0/0",
    "ast": "0/0",
    "stl": "-",
    "blk": "-",
    "fgPct": "-",
    "fg3Pct": "-",
    "ftPct": "-",
    "to": "-"
  },
  {
    "season": "",
    "gp": "-",
    "min": "-",
    "pts": "-",
    "reb": "0/0",
    "ast": "0/0",
    "stl": "-",
    "blk": "-",
    "fgPct": "-",
    "fg3Pct": "-",
    "ftPct": "-",
    "to": "-"
  },
  {
    "season": "",
    "gp": "-",
    "min": "-",
    "pts": "-",
    "reb": "0/0",
    "ast": "0/0",
    "stl": "-",
    "blk": "-",
    "fgPct": "-",
    "fg3Pct": "-",
    "ftPct": "-",
    "to": "-"
  },
  {
    "season": "",
    "gp": "-",
    "min": "-",
    "pts": "-",
    "reb": "0/0",
    "ast": "0/0",
    "stl": "-",
    "blk": "-",
    "fgPct": "-",
    "fg3Pct": "-",
    "ftPct": "-",
    "to": "-"
  },
  {
    "season": "",
    "gp": "-",
    "min": "-",
    "pts": "-",
    "reb": "0/0",
    "ast": "0/0",
    "stl": "-",
    "blk": "-",
    "fgPct": "-",
    "fg3Pct": "-",
    "ftPct": "-",
    "to": "-"
  },
  {
    "season": "",
    "gp": "-",
    "min": "-",
    "pts": "-",
    "reb": "4/5",
    "ast": "4/5",
    "stl": "-",
    "blk": "-",
    "fgPct": "-",
    "fg3Pct": "-",
    "ftPct": "-",
    "to": "-"
  },
  {
    "season": "",
    "gp": "-",
    "min": "-",
    "pts": "-",
    "reb": "7/10",
    "ast": "7/10",
    "stl": "-",
    "blk": "-",
    "fgPct": "-",
    "fg3Pct": "-",
    "ftPct": "-",
    "to": "-"
  },
  {
    "season": "",
    "gp": "-",
    "min": "-",
    "pts": "-",
    "reb": "12/16",
    "ast": "12/16",
    "stl": "-",
    "blk": "-",
    "fgPct": "-",
    "fg3Pct": "-",
    "ftPct": "-",
    "to": "-"
  },
  {
    "season": "",
    "gp": "-",
    "min": "-",
    "pts": "-",
    "reb": "2/4",
    "ast": "2/4",
    "stl": "-",
    "blk": "-",
    "fgPct": "-",
    "fg3Pct": "-",
    "ftPct": "-",
    "to": "-"
  },
  {
    "season": "",
    "gp": "-",
    "min": "-",
    "pts": "-",
    "reb": "6/7",
    "ast": "6/7",
    "stl": "-",
    "blk": "-",
    "fgPct": "-",
    "fg3Pct": "-",
    "ftPct": "-",
    "to": "-"
  },
  {
    "season": "",
    "gp": "-",
    "min": "-",
    "pts": "-",
    "reb": "9/10",
    "ast": "9/10",
    "stl": "-",
    "blk": "-",
    "fgPct": "-",
    "fg3Pct": "-",
    "ftPct": "-",
    "to": "-"
  },
  {
    "season": "",
    "gp": "-",
    "min": "-",
    "pts": "-",
    "reb": "31/36",
    "ast": "31/36",
    "stl": "-",
    "blk": "-",
    "fgPct": "-",
    "fg3Pct": "-",
    "ftPct": "-",
    "to": "-"
  },
  {
    "season": "",
    "gp": "-",
    "min": "-",
    "pts": "-",
    "reb": "7/13",
    "ast": "7/13",
    "stl": "-",
    "blk": "-",
    "fgPct": "-",
    "fg3Pct": "-",
    "ftPct": "-",
    "to": "-"
  },
  {
    "season": "",
    "gp": "-",
    "min": "-",
    "pts": "-",
    "reb": "45/59",
    "ast": "45/59",
    "stl": "-",
    "blk": "-",
    "fgPct": "-",
    "fg3Pct": "-",
    "ftPct": "-",
    "to": "-"
  },
  {
    "season": "",
    "gp": "-",
    "min": "-",
    "pts": "-",
    "reb": "2/4",
    "ast": "2/4",
    "stl": "-",
    "blk": "-",
    "fgPct": "-",
    "fg3Pct": "-",
    "ftPct": "-",
    "to": "-"
  }
]
