{
  "id": "jagrja01",
  "espnId": "405",
  "slug": "jagrja01",
  "name": "Jaromir Jagr",
  "sport": "nhl",
  "position": "RW",
  "team": "CGY",
  "headshot": "media/headshots/nhl/jagrja01.png",
  "headshotSource": "https://a.espncdn.com/i/headshots/nhl/players/full/405.png",
  "legend": true,
  "seasonHistory": [
    {
      "season": "17-18",
      "team": "CGY",
      "gp": "22",
      "min": "-",
      "pts": "7",
      "reb": "1",
      "ast": "6",
      "stl": "6",
      "blk": "-",
      "fgPct": "-",
      "fg3Pct": "-",
      "ftPct": "-",
      "to": "-"
    },
    {
      "season": "16-17",
      "team": "FLA",
      "gp": "82",
      "min": "-",
      "pts": "46",
      "reb": "16",
      "ast": "30",
      "stl": "2",
      "blk": "-",
      "fgPct": "-",
      "fg3Pct": "-",
      "ftPct": "-",
      "to": "-"
    },
    {
      "season": "15-16",
      "team": "FLA",
      "gp": "79",
      "min": "-",
      "pts": "66",
      "reb": "27",
      "ast": "39",
      "stl": "23",
      "blk": "-",
      "fgPct": "-",
      "fg3Pct": "-",
      "ftPct": "-",
      "to": "-"
    },
    {
      "season": "14-15",
      "gp": "77",
      "min": "-",
      "pts": "47",
      "reb": "17",
      "ast": "30",
      "stl": "-3",
      "blk": "-",
      "fgPct": "-",
      "fg3Pct": "-",
      "ftPct": "-",
      "to": "-"
    },
    {
      "season": "14-15",
      "team": "FLA",
      "gp": "20",
      "min": "-",
      "pts": "18",
      "reb": "6",
      "ast": "12",
      "stl": "7",
      "blk": "-",
      "fgPct": "-",
      "fg3Pct": "-",
      "ftPct": "-",
      "to": "-"
    },
    {
      "season": "14-15",
      "team": "NJ",
      "gp": "57",
      "min": "-",
      "pts": "29",
      "reb": "11",
      "ast": "18",
      "stl": "-10",
      "blk": "-",
      "fgPct": "-",
      "fg3Pct": "-",
      "ftPct": "-",
      "to": "-"
    },
    {
      "season": "13-14",
      "team": "NJ",
      "gp": "82",
      "min": "-",
      "pts": "67",
      "reb": "24",
      "ast": "43",
      "stl": "16",
      "blk": "-",
      "fgPct": "-",
      "fg3Pct": "-",
      "ftPct": "-",
      "to": "-"
    },
    {
      "season": "12-13",
      "gp": "45",
      "min": "-",
      "pts": "35",
      "reb": "16",
      "ast": "19",
      "stl": "-2",
      "blk": "-",
      "fgPct": "-",
      "fg3Pct": "-",
      "ftPct": "-",
      "to": "-"
    },
    {
      "season": "12-13",
      "team": "DAL",
      "gp": "34",
      "min": "-",
      "pts": "26",
      "reb": "14",
      "ast": "12",
      "stl": "-5",
      "blk": "-",
      "fgPct": "-",
      "fg3Pct": "-",
      "ftPct": "-",
      "to": "-"
    },
    {
      "season": "12-13",
      "team": "BOS",
      "gp": "11",
      "min": "-",
      "pts": "9",
      "reb": "2",
      "ast": "7",
      "stl": "3",
      "blk": "-",
      "fgPct": "-",
      "fg3Pct": "-",
      "ftPct": "-",
      "to": "-"
    },
    {
      "season": "11-12",
      "team": "PHI",
      "gp": "73",
      "min": "-",
      "pts": "54",
      "reb": "19",
      "ast": "35",
      "stl": "5",
      "blk": "-",
      "fgPct": "-",
      "fg3Pct": "-",
      "ftPct": "-",
      "to": "-"
    },
    {
      "season": "07-08",
      "team": "NYR",
      "gp": "82",
      "min": "-",
      "pts": "71",
      "reb": "25",
      "ast": "46",
      "stl": "8",
      "blk": "-",
      "fgPct": "-",
      "fg3Pct": "-",
      "ftPct": "-",
      "to": "-"
    },
    {
      "season": "06-07",
      "team": "NYR",
      "gp": "82",
      "min": "-",
      "pts": "96",
      "reb": "30",
      "ast": "66",
      "stl": "26",
      "blk": "-",
      "fgPct": "-",
      "fg3Pct": "-",
      "ftPct": "-",
      "to": "-"
    },
    {
      "season": "05-06",
      "team": "NYR",
      "gp": "82",
      "min": "-",
      "pts": "123",
      "reb": "54",
      "ast": "69",
      "stl": "34",
      "blk": "-",
      "fgPct": "-",
      "fg3Pct": "-",
      "ftPct": "-",
      "to": "-"
    },
    {
      "season": "03-04",
      "gp": "77",
      "min": "-",
      "pts": "74",
      "reb": "31",
      "ast": "43",
      "stl": "-5",
      "blk": "-",
      "fgPct": "-",
      "fg3Pct": "-",
      "ftPct": "-",
      "to": "-"
    },
    {
      "season": "03-04",
      "team": "WSH",
      "gp": "46",
      "min": "-",
      "pts": "45",
      "reb": "16",
      "ast": "29",
      "stl": "-4",
      "blk": "-",
      "fgPct": "-",
      "fg3Pct": "-",
      "ftPct": "-",
      "to": "-"
    },
    {
      "season": "03-04",
      "team": "NYR",
      "gp": "31",
      "min": "-",
      "pts": "29",
      "reb": "15",
      "ast": "14",
      "stl": "-1",
      "blk": "-",
      "fgPct": "-",
      "fg3Pct": "-",
      "ftPct": "-",
      "to": "-"
    },
    {
      "season": "02-03",
      "team": "WSH",
      "gp": "75",
      "min": "-",
      "pts": "77",
      "reb": "36",
      "ast": "41",
      "stl": "5",
      "blk": "-",
      "fgPct": "-",
      "fg3Pct": "-",
      "ftPct": "-",
      "to": "-"
    },
    {
      "season": "01-02",
      "team": "WSH",
      "gp": "69",
      "min": "-",
      "pts": "79",
      "reb": "31",
      "ast": "48",
      "stl": "0",
      "blk": "-",
      "fgPct": "-",
      "fg3Pct": "-",
      "ftPct": "-",
      "to": "-"
    },
    {
      "season": "00-01",
      "team": "PIT",
      "gp": "81",
      "min": "-",
      "pts": "121",
      "reb": "52",
      "ast": "69",
      "stl": "19",
      "blk": "-",
      "fgPct": "-",
      "fg3Pct": "-",
      "ftPct": "-",
      "to": "-"
    },
    {
      "season": "99-00",
      "team": "PIT",
      "gp": "63",
      "min": "-",
      "pts": "96",
      "reb": "42",
      "ast": "54",
      "stl": "25",
      "blk": "-",
      "fgPct": "-",
      "fg3Pct": "-",
      "ftPct": "-",
      "to": "-"
    },
    {
      "season": "98-99",
      "team": "PIT",
      "gp": "81",
      "min": "-",
      "pts": "127",
      "reb": "44",
      "ast": "83",
      "stl": "17",
      "blk": "-",
      "fgPct": "-",
      "fg3Pct": "-",
      "ftPct": "-",
      "to": "-"
    },
    {
      "season": "97-98",
      "team": "PIT",
      "gp": "77",
      "min": "-",
      "pts": "102",
      "reb": "35",
      "ast": "67",
      "stl": "17",
      "blk": "-",
      "fgPct": "-",
      "fg3Pct": "-",
      "ftPct": "-",
      "to": "-"
    },
    {
      "season": "96-97",
      "team": "PIT",
      "gp": "63",
      "min": "-",
      "pts": "95",
      "reb": "47",
      "ast": "48",
      "stl": "22",
      "blk": "-",
      "fgPct": "-",
      "fg3Pct": "-",
      "ftPct": "-",
      "to": "-"
    },
    {
      "season": "95-96",
      "team": "PIT",
      "gp": "82",
      "min": "-",
      "pts": "149",
      "reb": "62",
      "ast": "87",
      "stl": "31",
      "blk": "-",
      "fgPct": "-",
      "fg3Pct": "-",
      "ftPct": "-",
      "to": "-"
    },
    {
      "season": "95-95",
      "team": "PIT",
      "gp": "48",
      "min": "-",
      "pts": "70",
      "reb": "32",
      "ast": "38",
      "stl": "23",
      "blk": "-",
      "fgPct": "-",
      "fg3Pct": "-",
      "ftPct": "-",
      "to": "-"
    },
    {
      "season": "93-94",
      "team": "PIT",
      "gp": "80",
      "min": "-",
      "pts": "99",
      "reb": "32",
      "ast": "67",
      "stl": "15",
      "blk": "-",
      "fgPct": "-",
      "fg3Pct": "-",
      "ftPct": "-",
      "to": "-"
    },
    {
      "season": "92-93",
      "team": "PIT",
      "gp": "81",
      "min": "-",
      "pts": "94",
      "reb": "34",
      "ast": "60",
      "stl": "30",
      "blk": "-",
      "fgPct": "-",
      "fg3Pct": "-",
      "ftPct": "-",
      "to": "-"
    },
    {
      "season": "91-92",
      "team": "PIT",
      "gp": "70",
      "min": "-",
      "pts": "69",
      "reb": "32",
      "ast": "37",
      "stl": "12",
      "blk": "-",
      "fgPct": "-",
      "fg3Pct": "-",
      "ftPct": "-",
      "to": "-"
    },
    {
      "season": "90-91",
      "team": "PIT",
      "gp": "80",
      "min": "-",
      "pts": "57",
      "reb": "27",
      "ast": "30",
      "stl": "-4",
      "blk": "-",
      "fgPct": "-",
      "fg3Pct": "-",
      "ftPct": "-",
      "to": "-"
    }
  ],
  "recentGames": [
    {
      "date": "Dec 31",
      "matchup": "vs CHI",
      "result": "W 4-3 OT",
      "min": "—",
      "pts": "0",
      "reb": "0",
      "ast": "0",
      "stl": "-1",
      "blk": "—"
    },
    {
      "date": "Dec 29",
      "matchup": "@ ANA",
      "result": "L 2-1",
      "min": "—",
      "pts": "0",
      "reb": "0",
      "ast": "0",
      "stl": "-1",
      "blk": "—"
    },
    {
      "date": "Dec 28",
      "matchup": "@ SJ",
      "result": "L 3-2 SO",
      "min": "—",
      "pts": "0",
      "reb": "0",
      "ast": "0",
      "stl": "0",
      "blk": "—"
    },
    {
      "date": "Dec 17",
      "matchup": "@ VAN",
      "result": "W 6-1",
      "min": "—",
      "pts": "0",
      "reb": "0",
      "ast": "0",
      "stl": "1",
      "blk": "—"
    },
    {
      "date": "Dec 16",
      "matchup": "vs NSH",
      "result": "L 2-0",
      "min": "—",
      "pts": "0",
      "reb": "0",
      "ast": "0",
      "stl": "0",
      "blk": "—"
    }
  ],
  "sources": [
    "espn"
  ],
  "ingestedAt": "2026-06-17T03:25:48.192Z"
}
